n2yo/__init__.py
n2yo-0.0.5.dist-info/LICENSE
n2yo-0.0.5.dist-info/METADATA
n2yo-0.0.5.dist-info/WHEEL
n2yo-0.0.5.dist-info/top_level.txt
n2yo-0.0.5.dist-info/RECORD
