Metadata-Version: 2.1
Name: n2yo
Version: 0.0.5
Summary: Python wrapper for the N2YO API
Home-page: https://github.com/circuitqed/n2yo
Author: David Schuster
Author-email: David.Schuster@gmail.com
License: UNKNOWN
Platform: UNKNOWN
Classifier: Programming Language :: Python :: 3
Classifier: License :: OSI Approved :: MIT License
Classifier: Operating System :: OS Independent
Requires-Dist: requests
